apigateway/__init__.py
apigateway/clients/__init__.py
apigateway/clients/client.py
apigateway/clients/constants.py
apigateway/exceptions/__init__.py
apigateway/exceptions/exceptions.py
apigateway/models/__init__.py
apigateway/models/consumer.py
apigateway/models/plugin_config.py
apigateway/models/route.py
apigateway/models/upstream.py
apigateway/models/upstream_host.py
viettel_api_gateway-0.1.dist-info/LICENSE.txt
viettel_api_gateway-0.1.dist-info/METADATA
viettel_api_gateway-0.1.dist-info/WHEEL
viettel_api_gateway-0.1.dist-info/top_level.txt
viettel_api_gateway-0.1.dist-info/RECORD
