Metadata-Version: 2.1
Name: viettel-api-gateway
Version: 0.1
Summary: Viettel Cloud API Gateway SDK
Home-page: UNKNOWN
Author: trongnp3
Author-email: trongnp3@viettel.com.vn
License: UNKNOWN
Platform: UNKNOWN
Classifier: Programming Language :: Python :: 3
Classifier: License :: OSI Approved :: MIT License
Classifier: Operating System :: OS Independent
Requires-Python: >=3.6
Requires-Dist: requests (==2.28.2)
